setup.cfg
setup.py
text_to_csv/TxtToCsv.py
text_to_csv/__init__.py
text_to_csv.egg-info/PKG-INFO
text_to_csv.egg-info/SOURCES.txt
text_to_csv.egg-info/dependency_links.txt
text_to_csv.egg-info/not-zip-safe
text_to_csv.egg-info/top_level.txt