Metadata-Version: 1.0
Name: text-to-csv
Version: 0.0
Summary: Converter for txt-file into csv-file on Python
Home-page: UNKNOWN
Author: UNKNOWN
Author-email: george_zakharov@mail.ru
License: UNKNOWN
Platform: UNKNOWN
